xpecgen/__init__.py
xpecgen/xpecgen.py
xpecgen/xpecgenGUI.py
xpecgen/data/readme.md
xpecgen/data/cs/74.csv
xpecgen/data/cs/grid.csv
xpecgen/data/cs/readme.md
xpecgen/data/csda/74.csv
xpecgen/data/csda/GetCSDA.nb
xpecgen/data/csda/readme.md
xpecgen/data/fluence/100.csv
xpecgen/data/fluence/125.csv
xpecgen/data/fluence/150.csv
xpecgen/data/fluence/20.csv
xpecgen/data/fluence/200.csv
xpecgen/data/fluence/250.csv
xpecgen/data/fluence/300.csv
xpecgen/data/fluence/350.csv
xpecgen/data/fluence/400.csv
xpecgen/data/fluence/50.csv
xpecgen/data/fluence/80.csv
xpecgen/data/fluence/grid.csv
xpecgen/data/fluence/readme.md
xpecgen/data/fluence2dose/f2d.csv
xpecgen/data/fluence2dose/readme.md
xpecgen/data/mu/13.csv
xpecgen/data/mu/29.csv
xpecgen/data/mu/4.csv
xpecgen/data/mu/50.csv
xpecgen/data/mu/73.csv
xpecgen/data/mu/74.csv
xpecgen/data/mu/GetMu.nb
xpecgen/data/mu/air.csv
xpecgen/data/mu/readme.md
xpecgen-1.0.0.dist-info/DESCRIPTION.rst
xpecgen-1.0.0.dist-info/METADATA
xpecgen-1.0.0.dist-info/RECORD
xpecgen-1.0.0.dist-info/WHEEL
xpecgen-1.0.0.dist-info/entry_points.txt
xpecgen-1.0.0.dist-info/metadata.json
xpecgen-1.0.0.dist-info/top_level.txt
