Metadata-Version: 2.0
Name: xpecgen
Version: 1.0.0
Summary: A package with a GUI to calculate X-ray sPECtra GENerated in tungsten anodes
Home-page: https://github.com/Dih5/xpecgen
Author: Dih5
Author-email: guillehg@gmail.com
License: GPLv3
Keywords: X-ray spectra,Tungsten anode,Computer modeling
Platform: UNKNOWN
Classifier: Development Status :: 5 - Production/Stable
Classifier: Intended Audience :: Science/Research
Classifier: Topic :: Scientific/Engineering :: Medical Science Apps.
Classifier: License :: OSI Approved :: GNU General Public License v3 (GPLv3)
Classifier: Programming Language :: Python :: 3
Classifier: Programming Language :: Python :: 3.3
Classifier: Programming Language :: Python :: 3.4
Classifier: Programming Language :: Python :: 3.5
Requires-Dist: XlsxWriter
Requires-Dist: matplotlib
Requires-Dist: numpy
Requires-Dist: scipy
Provides-Extra: dev
Requires-Dist: check-manifest; extra == 'dev'
Provides-Extra: test
Requires-Dist: coverage; extra == 'test'
